pyetg1510/__init__.py
pyetg1510/etg_1510.py
pyetg1510/helper/__init__.py
pyetg1510/helper/logging_service.py
pyetg1510/helper/settings.py
pyetg1510/mailbox/__init__.py
pyetg1510/mailbox/connection.py
pyetg1510/mailbox/mailbox_gateway.py
pyetg1510/mailbox/sdo_application_interface.py
pyetg1510/sdo_1xxx_master_object.py
pyetg1510/sdo_8xxx_configuration_data.py
pyetg1510/sdo_9xxx_information_data.py
pyetg1510/sdo_axxx_master_diagnosis.py
pyetg1510/sdo_fxxx_controls.py
pyetg1510/topology.py
pyetg1510-0.1.3.dist-info/LICENSE
pyetg1510-0.1.3.dist-info/METADATA
pyetg1510-0.1.3.dist-info/WHEEL
pyetg1510-0.1.3.dist-info/RECORD
