Metadata-Version: 2.1
Name: pyetg1510
Version: 0.1.3
Summary: ETG.1510 EtherCAT Master Diagnosis Interface client library for Python
Home-page: https://ta-ichihashi.github.io/PyETG1510/index.html
License: BSD-4-Clause
Author: Takashi Ichihashi
Author-email: t.ichihashi@bekchoff.co.jp
Requires-Python: >=3.9,<4.0
Classifier: License :: Other/Proprietary License
Classifier: Programming Language :: Python :: 3
Classifier: Programming Language :: Python :: 3.9
Classifier: Programming Language :: Python :: 3.10
Classifier: Programming Language :: Python :: 3.11
Classifier: Topic :: Software Development :: Libraries :: Python Modules
Requires-Dist: bitarray (>=2.8.2,<3.0.0)
Requires-Dist: poethepoet (>=0.24.0,<0.25.0)
Project-URL: Repository, https://github.com/ta-ichihashi/PyETG1510
